Metadata-Version: 2.4
Name: robot_prefect
Version: 1.0.4
Summary: Workflow orchestration and management.
Project-URL: Changelog, https://github.com/anilpixel/rebot-prefect/releases
Project-URL: Documentation, https://docs.prefect.io
Project-URL: Source, https://github.com/anilpixel/rebot-prefect
Project-URL: Tracker, https://github.com/anilpixel/rebot-prefect/issues
Author-email: anilpixel <eziosyanse@gmail.com>
License: Apache-2.0
License-File: LICENSE
Classifier: Intended Audience :: Developers
Classifier: Intended Audience :: System Administrators
Classifier: License :: OSI Approved :: Apache Software License
Classifier: Natural Language :: English
Classifier: Programming Language :: Python :: 3 :: Only
Classifier: Programming Language :: Python :: 3.9
Classifier: Programming Language :: Python :: 3.10
Classifier: Programming Language :: Python :: 3.11
Classifier: Programming Language :: Python :: 3.12
Classifier: Programming Language :: Python :: 3.13
Classifier: Topic :: Software Development :: Libraries
Requires-Python: <3.14,>=3.9
Requires-Dist: anyio<5.0.0,>=4.4.0
Requires-Dist: asgi-lifespan<3.0,>=1.0
Requires-Dist: cachetools<7.0,>=5.3
Requires-Dist: cloudpickle<4.0,>=2.0
Requires-Dist: coolname<3.0.0,>=1.0.4
Requires-Dist: exceptiongroup>=1.0.0
Requires-Dist: fastapi<1.0.0,>=0.111.0
Requires-Dist: fsspec>=2022.5.0
Requires-Dist: graphviz>=0.20.1
Requires-Dist: griffe<2.0.0,>=0.49.0
Requires-Dist: httpcore<2.0.0,>=1.0.5
Requires-Dist: httpx[http2]!=0.23.2,>=0.23
Requires-Dist: humanize<5.0.0,>=4.9.0
Requires-Dist: importlib-metadata>=4.4; python_version < '3.10'
Requires-Dist: jsonpatch<2.0,>=1.32
Requires-Dist: opentelemetry-api<2.0.0,>=1.27.0
Requires-Dist: packaging<25.1,>=21.3
Requires-Dist: pathspec>=0.8.0
Requires-Dist: pendulum<4,>=3.0.0; python_version < '3.13'
Requires-Dist: pluggy>=1.6.0
Requires-Dist: prometheus-client>=0.20.0
Requires-Dist: pydantic!=2.11.0,!=2.11.1,!=2.11.2,!=2.11.3,!=2.11.4,<3.0.0,>=2.10.1
Requires-Dist: pydantic-core<3.0.0,>=2.12.0
Requires-Dist: pydantic-extra-types<3.0.0,>=2.8.2
Requires-Dist: pydantic-settings!=2.9.0,<3.0.0,>2.2.1
Requires-Dist: python-dateutil<3.0.0,>=2.8.2
Requires-Dist: python-slugify<9.0,>=5.0
Requires-Dist: pyyaml<7.0.0,>=5.4.1
Requires-Dist: readchar<5.0.0,>=4.0.0
Requires-Dist: rfc3339-validator<0.2.0,>=0.1.4
Requires-Dist: rich<15.0,>=11.0
Requires-Dist: ruamel-yaml>=0.17.0
Requires-Dist: semver>=3.0.4
Requires-Dist: sniffio<2.0.0,>=1.3.0
Requires-Dist: toml>=0.10.0
Requires-Dist: typer!=0.12.2,<0.20.0,>=0.12.0
Requires-Dist: typing-extensions<5.0.0,>=4.10.0
Requires-Dist: uv>=0.6.0
Requires-Dist: uvicorn!=0.29.0,>=0.14.0
Requires-Dist: websockets<16.0,>=15.0.1
Requires-Dist: whenever<0.10.0,>=0.7.3; python_version >= '3.13'
Provides-Extra: aws
Requires-Dist: prefect-aws>=0.5.8; extra == 'aws'
Provides-Extra: azure
Requires-Dist: prefect-azure>=0.4.0; extra == 'azure'
Provides-Extra: bitbucket
Requires-Dist: prefect-bitbucket>=0.3.0; extra == 'bitbucket'
Provides-Extra: dask
Requires-Dist: prefect-dask>=0.3.0; extra == 'dask'
Provides-Extra: databricks
Requires-Dist: prefect-databricks>=0.3.0; extra == 'databricks'
Provides-Extra: dbt
Requires-Dist: prefect-dbt>=0.6.0; extra == 'dbt'
Provides-Extra: docker
Requires-Dist: prefect-docker>=0.6.0; extra == 'docker'
Provides-Extra: email
Requires-Dist: prefect-email>=0.4.0; extra == 'email'
Provides-Extra: gcp
Requires-Dist: prefect-gcp>=0.6.0; extra == 'gcp'
Provides-Extra: github
Requires-Dist: prefect-github>=0.3.0; extra == 'github'
Provides-Extra: gitlab
Requires-Dist: prefect-gitlab>=0.3.0; extra == 'gitlab'
Provides-Extra: kubernetes
Requires-Dist: prefect-kubernetes>=0.4.0; extra == 'kubernetes'
Provides-Extra: otel
Requires-Dist: opentelemetry-distro<1.0.0,>=0.48b0; extra == 'otel'
Requires-Dist: opentelemetry-exporter-otlp<2.0.0,>=1.27.0; extra == 'otel'
Requires-Dist: opentelemetry-instrumentation-logging<1.0.0,>=0.48b0; extra == 'otel'
Requires-Dist: opentelemetry-instrumentation<1.0.0,>=0.48b0; extra == 'otel'
Requires-Dist: opentelemetry-test-utils<1.0.0,>=0.48b0; extra == 'otel'
Provides-Extra: ray
Requires-Dist: prefect-ray>=0.4.0; extra == 'ray'
Provides-Extra: redis
Requires-Dist: prefect-redis>=0.2.0; extra == 'redis'
Provides-Extra: shell
Requires-Dist: prefect-shell>=0.3.0; extra == 'shell'
Provides-Extra: slack
Requires-Dist: prefect-slack>=0.3.0; extra == 'slack'
Provides-Extra: snowflake
Requires-Dist: prefect-snowflake>=0.28.0; extra == 'snowflake'
Provides-Extra: sqlalchemy
Requires-Dist: prefect-sqlalchemy>=0.5.0; extra == 'sqlalchemy'
